LICENSE
README.md
setup.py
mailcoil/CMS.py
mailcoil/Email.py
mailcoil/Exceptions.py
mailcoil/FriendlyArgumentParser.py
mailcoil/MailDropoff.py
mailcoil/SerializedEmail.py
mailcoil/__init__.py
mailcoil/__main__.py
mailcoil.egg-info/PKG-INFO
mailcoil.egg-info/SOURCES.txt
mailcoil.egg-info/dependency_links.txt
mailcoil.egg-info/entry_points.txt
mailcoil.egg-info/top_level.txt